Metadata-Version: 2.4
Name: heretic-llm
Version: 1.0.1
Summary: Fully automatic censorship removal for language models
Keywords: llm,transformer,abliteration
Author: Philipp Emanuel Weidmann
Author-email: Philipp Emanuel Weidmann <pew@worldwidemann.com>
License-Expression: AGPL-3.0-or-later
Classifier: Development Status :: 4 - Beta
Classifier: Environment :: Console
Classifier: Environment :: GPU
Classifier: Intended Audience :: Science/Research
Classifier: License :: OSI Approved :: GNU Affero General Public License v3 or later (AGPLv3+)
Classifier: Topic :: Scientific/Engineering :: Artificial Intelligence
Classifier: Programming Language :: Python :: 3
Classifier: Programming Language :: Python :: 3.10
Classifier: Programming Language :: Python :: 3.11
Classifier: Programming Language :: Python :: 3.12
Requires-Dist: accelerate>=1.10.0
Requires-Dist: datasets>=4.0.0
Requires-Dist: hf-transfer>=0.1.9
Requires-Dist: huggingface-hub>=0.34.4
Requires-Dist: optuna>=4.5.0
Requires-Dist: pydantic-settings>=2.10.1
Requires-Dist: questionary>=2.1.1
Requires-Dist: rich>=14.1.0
Requires-Dist: transformers>=4.55.2
Requires-Python: >=3.10
Project-URL: Changelog, https://github.com/p-e-w/heretic/commits/master/
Project-URL: Documentation, https://github.com/p-e-w/heretic
Project-URL: Homepage, https://github.com/p-e-w/heretic
Project-URL: Issues, https://github.com/p-e-w/heretic/issues
Project-URL: Repository, https://github.com/p-e-w/heretic.git
